CHANGELOG.md
CMakeLists.txt
CONTRIBUTING.md
LICENSE
MANIFEST.in
README
README.md
pyproject.toml
setup.py
caliby.egg-info/PKG-INFO
caliby.egg-info/SOURCES.txt
caliby.egg-info/dependency_links.txt
caliby.egg-info/not-zip-safe
caliby.egg-info/requires.txt
caliby.egg-info/top_level.txt
include/caliby/aligned_allocator.hpp
include/caliby/calico.hpp
include/caliby/catalog.hpp
include/caliby/diskann.hpp
include/caliby/distance.hpp
include/caliby/distance_diskann.hpp
include/caliby/exmap.h
include/caliby/hash_tables.hpp
include/caliby/hnsw.hpp
include/caliby/ivfpq.hpp
include/caliby/perf_util.hpp
include/caliby/simd_utils.hpp
include/caliby/utils.hpp
include/caliby/tpcc/RandomGenerator.hpp
include/caliby/tpcc/Schema.hpp
include/caliby/tpcc/TPCCWorkload.hpp
include/caliby/tpcc/Types.hpp
include/caliby/tpcc/ZipfianGenerator.hpp
src/bindings.cpp
src/calico.cpp
src/catalog.cpp
src/diskann.cpp
src/distance_diskann.cpp
src/hnsw.cpp
src/ivfpq.cpp
tests/test_catalog.py
tests/test_diskann.py
tests/test_distance.py
tests/test_force_eviction.py
tests/test_hnsw.py
tests/test_hole_punching.py
tests/test_hole_punching_direct.py
tests/test_hole_punching_validation.py
tests/test_index_persistence.py
tests/test_initialization.py
tests/test_integration.py
tests/test_ivfpq.py
tests/test_ivfpq_extensive.py
tests/test_multi_index.py
tests/test_multi_index_direct.py
tests/test_recovery.py
third_party/pybind11/.appveyor.yml
third_party/pybind11/.clang-format
third_party/pybind11/.clang-tidy
third_party/pybind11/.cmake-format.yaml
third_party/pybind11/.codespell-ignore-lines
third_party/pybind11/.git
third_party/pybind11/.gitattributes
third_party/pybind11/.gitignore
third_party/pybind11/.pre-commit-config.yaml
third_party/pybind11/.readthedocs.yml
third_party/pybind11/CMakeLists.txt
third_party/pybind11/CMakePresets.json
third_party/pybind11/LICENSE
third_party/pybind11/README.rst
third_party/pybind11/SECURITY.md
third_party/pybind11/noxfile.py
third_party/pybind11/pyproject.toml
third_party/pybind11/.github/CODEOWNERS
third_party/pybind11/.github/CONTRIBUTING.md
third_party/pybind11/.github/dependabot.yml
third_party/pybind11/.github/labeler.yml
