Metadata-Version: 2.4
Name: caliby
Version: 0.1.1
Summary: High-Performance Disk-Aware Vector Search Library
Home-page: https://github.com/caliby/caliby
Author: Caliby Contributors
Author-email: caliby@example.com
License-Expression: MIT
Project-URL: Homepage, https://github.com/zxjcarrot/caliby
Project-URL: Documentation, https://github.com/zxjcarrot/caliby#readme
Project-URL: Repository, https://github.com/zxjcarrot/caliby
Project-URL: Issues, https://github.com/zxjcarrot/caliby/issues
Keywords: vector-search,approximate-nearest-neighbors,hnsw,diskann,similarity-search,embeddings,machine-learning
Classifier: Development Status :: 4 - Beta
Classifier: Intended Audience :: Developers
Classifier: Intended Audience :: Science/Research
Classifier: Operating System :: POSIX :: Linux
Classifier: Programming Language :: C++
Classifier: Programming Language :: Python :: 3
Classifier: Programming Language :: Python :: 3.8
Classifier: Programming Language :: Python :: 3.9
Classifier: Programming Language :: Python :: 3.10
Classifier: Programming Language :: Python :: 3.11
Classifier: Programming Language :: Python :: 3.12
Classifier: Topic :: Scientific/Engineering :: Artificial Intelligence
Classifier: Topic :: Database :: Database Engines/Servers
Requires-Python: >=3.8
License-File: LICENSE
Requires-Dist: numpy>=1.19.0
Provides-Extra: dev
Requires-Dist: pytest>=6.0; extra == "dev"
Requires-Dist: pytest-benchmark; extra == "dev"
Requires-Dist: numpy>=1.19.0; extra == "dev"
Dynamic: author-email
Dynamic: home-page
Dynamic: license-file
Dynamic: requires-python
